Tetis/__init__.py
Tetis/api/Curl_conf.py
Tetis/api/PycurlHelper.py
Tetis/api/RequestUtils.py
Tetis/api/RequestsHelper.py
Tetis/api/__init__.py
Tetis/base/CommonBase.py
Tetis/base/Env.py
Tetis/base/Files.py
Tetis/base/Frequency.py
Tetis/base/HttpResponse.py
Tetis/base/IP.py
Tetis/base/MQHelper.py
Tetis/base/MemcacheHelper.py
Tetis/base/MonitorAlert.py
Tetis/base/RedisHelper.py
Tetis/base/SendMail.py
Tetis/base/SqlAlchemySession.py
Tetis/base/__init__.py
Tetis/base/useragent.py
Tetis/plugins/__init__.py
Tetis/plugins/deathtrap_coral.py
Tetis/plugins/light_of_the_mermaid.py
Tetis/ui/android/__init__.py
Tetis/ui/ios/__init__.py
Tetis/ui/mobile/__init__.py
Tetis/ui/pc/__init__.py
Tetis/ui/pc/base_element.py
Tetis/ui/pc/base_page.py
Tetis/ui/pc/location.py
Tetis/ui/util/ElementFinder.py
Tetis/ui/util/__init__.py
Tetis-0.0.45.dist-info/METADATA
Tetis-0.0.45.dist-info/WHEEL
Tetis-0.0.45.dist-info/entry_points.txt
Tetis-0.0.45.dist-info/top_level.txt
Tetis-0.0.45.dist-info/RECORD
