Metadata-Version: 2.1
Name: Tetis
Version: 0.0.45
Summary: 基于Posedion项目中常用工具类插件
Home-page: http://qa.pip.yeshj.com/simple/tetis/
Author: songmengyun
Author-email: songmengyun@hujiang.com
License: UNKNOWN
Keywords: Poseidon,pytest
Platform: any
Classifier: Framework :: Pytest
Requires-Dist: PyYAML
Requires-Dist: requests
Requires-Dist: pytest
Requires-Dist: request
Requires-Dist: pytest-html
Requires-Dist: pytest-selenium
Requires-Dist: pytest-json
Requires-Dist: selenium
Requires-Dist: pytest-testconfig
Requires-Dist: redis
Requires-Dist: SQLAlchemy
Requires-Dist: urllib3
